afe/__init__.py
afe/features.py
AFE-2020.3.29.dist-info/METADATA
AFE-2020.3.29.dist-info/WHEEL
AFE-2020.3.29.dist-info/top_level.txt
AFE-2020.3.29.dist-info/RECORD
