Metadata-Version: 2.1
Name: AFE
Version: 2020.3.29
Summary: Accelerometer Feature Extractor
Home-page: https://bitbucket.org/atpage/afe
Author: Alex Page
Author-email: alex.page@rochester.edu
License: UNKNOWN
Keywords: accelerometer acceleration accelerometry gyroscope machine learning features
Platform: UNKNOWN
Requires-Python: >=3.0
Requires-Dist: actigraph
Requires-Dist: numpy
Requires-Dist: pandas
Requires-Dist: scipy
